pdfformread/__init__.py
pdfformread/command_line.py
pdfformread-0.1.2.dist-info/DESCRIPTION.rst
pdfformread-0.1.2.dist-info/METADATA
pdfformread-0.1.2.dist-info/RECORD
pdfformread-0.1.2.dist-info/WHEEL
pdfformread-0.1.2.dist-info/entry_points.txt
pdfformread-0.1.2.dist-info/metadata.json
pdfformread-0.1.2.dist-info/top_level.txt
