Metadata-Version: 2.0
Name: pdfformread
Version: 0.1.2
Summary: Extract form data from a PDF form.
Home-page: http://github.com/BartMassey/pdfformread
Author: Bart Massey
Author-email: bart.massey@gmail.com
License: MIT
Keywords: pdf form extract data
Platform: UNKNOWN
Classifier: Development Status :: 3 - Alpha
Classifier: License :: OSI Approved :: MIT License
Classifier: Programming Language :: Python :: 2.7
Classifier: Topic :: Office/Business
Requires-Dist: pdfminer
